avsec/__init__.py
avsec/analyze/__init__.py
avsec/attack/__init__.py
avsec/attack/image/__init__.py
avsec/attack/lidar/__init__.py
avsec/attack/lidar/attacker.py
avsec/attack/lidar/configs/false_positive_attacker.yaml
avsec/attack/lidar/configs/replay_attacker.yaml
avsec/attack/lidar/executor.py
avsec/attack/lidar/monitor.py
avsec/attack/lidar/scheduler.py
avsec/attack/lidar/utils.py
avsec/attack/types.py
avsec/defend/__init__.py
avsec/defend/lidar/__init__.py
avsec/utils.py
lib_avsec-0.1.0a1.dist-info/LICENSE.md
lib_avsec-0.1.0a1.dist-info/METADATA
lib_avsec-0.1.0a1.dist-info/WHEEL
lib_avsec-0.1.0a1.dist-info/RECORD
